README.md
setup.py
eve_rights/__init__.py
eve_rights/config.py
eve_rights/hooks.py
eve_rights/main.py
eve_rights.egg-info/PKG-INFO
eve_rights.egg-info/SOURCES.txt
eve_rights.egg-info/dependency_links.txt
eve_rights.egg-info/not-zip-safe
eve_rights.egg-info/top_level.txt