Metadata-Version: 1.0
Name: eve-rights
Version: 0.0.2
Summary: Handle per-item rights in your python-eve application
Home-page: http://github.com/SakiiR/eve-rights
Author: SakiiR
Author-email: sakiirlessons@gmail.com
License: MIT
Platform: UNKNOWN
